README.rst
setup.py
webcam_ftpry.py
bin/webcam-ftpry
webcam_ftpry.egg-info/PKG-INFO
webcam_ftpry.egg-info/SOURCES.txt
webcam_ftpry.egg-info/dependency_links.txt
webcam_ftpry.egg-info/requires.txt
webcam_ftpry.egg-info/top_level.txt