Metadata-Version: 1.1
Name: webcam-ftpry
Version: 1.0.5
Summary: Captures images from a web cam and uploads them to an FTP server
Home-page: https://bitbucket.org/parqueryopen/webcam-ftpry
Author: Marko Ristin
Author-email: marko@parquery.com
License: UNKNOWN
Keywords: webcam ftp image
Platform: UNKNOWN
Classifier: Development Status :: 5 - Production/Stable
Classifier: Intended Audience :: End Users/Desktop
Classifier: License :: OSI Approved :: MIT License
Classifier: Programming Language :: Python :: 3.5
